siebe/__init__.py
siebe/datastructuring.py
siebe/imports.py
siebe/media_file_handling.py
siebe/rename_writtenNumbersToDigits.py
siebe-0.3.dist-info/METADATA
siebe-0.3.dist-info/WHEEL
siebe-0.3.dist-info/top_level.txt
siebe-0.3.dist-info/RECORD
