Metadata-Version: 2.1
Name: siebe
Version: 0.3
Summary: Custom functions package
Author: Siebe Albers
Classifier: Development Status :: 3 - Alpha
Classifier: Intended Audience :: Developers
Classifier: License :: OSI Approved :: MIT License
Classifier: Programming Language :: Python :: 3
